articles/__init__.py
articles/admin.py
articles/filters.py
articles/forms.py
articles/how_to.md
articles/managers.py
articles/models.py
articles/signals.py
articles/tests.py
articles/views.py
articles/fixtures/articles.json
articles/fixtures/auth_users.json
articles/migrations/0001_initial.py
articles/migrations/__init__.py
articles/templates/all_content/article_detail.html
articles/templates/all_content/article_list.html
articles/templates/all_content/base.html
articles/templates/articles/entry_archive.html
articles/templates/articles/index.html
articles/templates/blogs/add_image.html
articles/templates/blogs/blog_list.html
articles/templates/blogs/entry_form.html
articles/templates/blogs/thank-you.html
articles/templates/blogs/includes/blog_extras.html
articles/templatetags/__init__.py
articles/templatetags/article_tags.py
articles/templatetags/linkroll_tags.py
articles/urls/__init__.py
articles/urls/article_urls.py
articles/urls/base_urls.py
articles/urls/blog_urls.py
tango_articles-0.13.0.dist-info/METADATA
tango_articles-0.13.0.dist-info/RECORD
tango_articles-0.13.0.dist-info/WHEEL
tango_articles-0.13.0.dist-info/top_level.txt
