Metadata-Version: 1.1
Name: tango-articles
Version: 0.13.0
Summary: Reusable Django articles/blog content app. Can be used with or without Tango.
Home-page: http://github.com/tBaxter/tango-articles
Author: Tim Baxter
Author-email: mail.baxter@gmail.com
License: LICENSE.txt
Platform: UNKNOWN
Classifier: Development Status :: 4 - Beta
Classifier: Environment :: Web Environment
Classifier: Framework :: Django
Classifier: Intended Audience :: Developers
Classifier: License :: OSI Approved :: MIT License
Classifier: Programming Language :: Python
Classifier: Programming Language :: Python :: 3.4
Classifier: Programming Language :: Python :: 3.5
